ispider-0.7.5.dist-info/licenses/LICENCE
ispider_core/__init__.py
ispider_core/__main__.py
ispider_core/api_server.py
ispider_core/config.py
ispider_core/ispider.py
ispider_core/orchestrator.py
ispider_core/settings.py
ispider_core/addons/out_parser_full_to_json.py
ispider_core/crawlers/cls_controllers.py
ispider_core/crawlers/cls_domain_stats.py
ispider_core/crawlers/cls_queue_out.py
ispider_core/crawlers/cls_seen_filter.py
ispider_core/crawlers/http_client.py
ispider_core/crawlers/http_filters.py
ispider_core/crawlers/http_retries.py
ispider_core/crawlers/stage_unified.py
ispider_core/crawlers/stage_unified_helpers.py
ispider_core/crawlers/thread_queue_in.py
ispider_core/crawlers/thread_save_finished.py
ispider_core/crawlers/thread_stats.py
ispider_core/engines/mod_curl.py
ispider_core/engines/mod_httpx.py
ispider_core/engines/mod_seleniumbase.py
ispider_core/parsers/email_parser.py
ispider_core/parsers/filetype_parser.py
ispider_core/parsers/html_parser.py
ispider_core/parsers/sitemaps_parser.py
ispider_core/parsers/social_parser.py
ispider_core/storage/json_storage.py
ispider_core/utils/domains.py
ispider_core/utils/efiles.py
ispider_core/utils/engine.py
ispider_core/utils/filters.py
ispider_core/utils/headers.py
ispider_core/utils/ifiles.py
ispider_core/utils/logger.py
ispider_core/utils/menu.py
ispider_core/utils/queues.py
ispider_core/utils/state_manager.py
tests/test_unified.py
ispider-0.7.5.dist-info/METADATA
ispider-0.7.5.dist-info/WHEEL
ispider-0.7.5.dist-info/entry_points.txt
ispider-0.7.5.dist-info/top_level.txt
ispider-0.7.5.dist-info/RECORD
