Metadata-Version: 2.4
Name: ispider
Version: 0.7.5
Summary: A high-speed web spider for massive scraping.
Author-email: Daniele Rugginenti <daniele.rugginenti@gmail.com>
License-Expression: MIT
Project-URL: Homepage, https://github.com/danruggi/ispider
License-File: LICENCE
Requires-Dist: aiohttp
Requires-Dist: beautifulsoup4
Requires-Dist: lxml
Requires-Dist: tqdm
Requires-Dist: requests
Requires-Dist: seleniumbase
Requires-Dist: httpx
Requires-Dist: nslookup
Requires-Dist: tldextract
Requires-Dist: concurrent_log_handler
Requires-Dist: colorlog
Requires-Dist: brotli
Requires-Dist: validators
Requires-Dist: w3lib
Requires-Dist: pybloom_live
Requires-Dist: uvicorn
Requires-Dist: fastapi
Requires-Dist: pandas
Dynamic: license-file
